cognica/__init__.py
cognica/channel.py
cognica/document_db.py
cognica/fts_analysis_pipeline.py
cognica/key_value_db.py
cognica/py.typed
cognica/sentence_transformer.py
cognica/system_metrics.py
cognica/protobuf/__init__.py
cognica/protobuf/document_db_pb2.py
cognica/protobuf/document_db_pb2_grpc.py
cognica/protobuf/document_pb2.py
cognica/protobuf/fts_analysis_pipeline_pb2.py
cognica/protobuf/fts_analysis_pipeline_pb2_grpc.py
cognica/protobuf/key_value_db_pb2.py
cognica/protobuf/key_value_db_pb2_grpc.py
cognica/protobuf/sentence_transformer_pb2.py
cognica/protobuf/sentence_transformer_pb2_grpc.py
cognica/protobuf/system_metrics_pb2.py
cognica/protobuf/system_metrics_pb2_grpc.py
cognica/protobuf/workspaces_pb2.py
cognica/protobuf/workspaces_pb2_grpc.py
cognica-0.1.17.dist-info/licenses/LICENSE
cognica-0.1.17.dist-info/METADATA
cognica-0.1.17.dist-info/WHEEL
cognica-0.1.17.dist-info/top_level.txt
cognica-0.1.17.dist-info/RECORD
