Metadata-Version: 2.4
Name: cognica
Version: 0.1.17
Summary: Python client for Cognica database
Author-email: "Cognica, Inc." <jaepil@cognica.io>
License:                                  Apache License
Project-URL: Homepage, https://www.cognica.io
Keywords: Cognica,key-value,document store,full-text search,vector search,search engine,database,deep learning,NLP,natural language processing,transformer,vector embedding
Classifier: Development Status :: 5 - Production/Stable
Classifier: Environment :: Console
Classifier: Intended Audience :: Developers
Classifier: License :: OSI Approved :: Apache Software License
Classifier: Operating System :: OS Independent
Classifier: Programming Language :: Python
Classifier: Programming Language :: Python :: 3
Classifier: Programming Language :: Python :: 3 :: Only
Classifier: Programming Language :: Python :: 3.9
Classifier: Programming Language :: Python :: 3.10
Classifier: Programming Language :: Python :: 3.11
Classifier: Programming Language :: Python :: Implementation :: CPython
Requires-Python: >=3.9
License-File: LICENSE
Requires-Dist: pandas>=1.5.3
Requires-Dist: polars>=0.16.18
Requires-Dist: pyarrow>=11.0.0
Requires-Dist: grpcio>=1.53.0
Requires-Dist: protobuf>=4.22.1
Requires-Dist: pillow
Provides-Extra: protobuf
Requires-Dist: grpcio>=1.43.0; extra == "protobuf"
Dynamic: license-file
